dronebl/__init__.py
dronebl/make.py
dronebl/parse.py
dronebl/py.typed
dronebl/struct.py
test/__init__.py
test/make.py
test/parse.py
dronebl-0.4.8.dist-info/LICENSE
dronebl-0.4.8.dist-info/METADATA
dronebl-0.4.8.dist-info/WHEEL
dronebl-0.4.8.dist-info/top_level.txt
dronebl-0.4.8.dist-info/RECORD
