Metadata-Version: 2.1
Name: dronebl
Version: 0.4.8
Summary: library to add, lookup and remove entries from DroneBL
Home-page: https://github.com/jesopo/pydronebl
Author: jesopo
Author-email: pip@jesopo.uk
License: UNKNOWN
Platform: UNKNOWN
Classifier: Programming Language :: Python :: 3
Classifier: License :: OSI Approved :: MIT License
Classifier: Operating System :: OS Independent
Classifier: Operating System :: POSIX
Classifier: Operating System :: Microsoft :: Windows
Requires-Python: >=3.6
Requires-Dist: httpx (==0.14.1)
